conpagnon
