Metadata-Version: 1.2
Name: conpagnon
Version: 2.0.10
Summary: Easy Resting State Analysis with Python
Home-page: https://conpagnon.github.io/conpagnon/
Maintainer: Dhaif BEKHA
Maintainer-email: dhaif@dhaifbekha.com
License: new BSD
Download-URL: https://github.com/ConPagnon/conpagnon/archive/v2.0.10.tar.gz
Platform: UNKNOWN
Classifier: Intended Audience :: Science/Research
Classifier: Intended Audience :: Developers
Classifier: License :: OSI Approved
Classifier: Programming Language :: C
Classifier: Programming Language :: Python
Classifier: Topic :: Software Development
Classifier: Topic :: Scientific/Engineering
Classifier: Operating System :: POSIX
Classifier: Operating System :: Unix
Classifier: Operating System :: MacOS
Classifier: Programming Language :: Python :: 3.6
Classifier: Programming Language :: Python :: 3.7
Classifier: Programming Language :: Python :: 3.8
Requires-Python: >=3.6
